notpy/__init__.py
notpy/modules/README.md
notpy/modules/commandline.py
notpy/modules/configure.py
notpy/modules/edit_md.py
notpy/modules/notebook.py
notpy/modules/read_md.py
notpy/modules/render_md.py
notpy/modules/show_md.py
notpy/modules/style.css
notpy/notpy.py
notpy-0.0.5.dist-info/LICENSE
notpy-0.0.5.dist-info/METADATA
notpy-0.0.5.dist-info/WHEEL
notpy-0.0.5.dist-info/entry_points.txt
notpy-0.0.5.dist-info/RECORD
