Metadata-Version: 2.1
Name: notpy
Version: 0.0.5
Summary: Create/Delete files and edit them as markdown files in your text editor
Home-page: https://github.com/jontok/Notpy
License: GPL-3.0-only
Keywords: notes,markdown,python,nvim,neovim
Author: jontok
Author-email: jonas@tokmaji.de
Requires-Python: >=3.10,<4.0
Classifier: Development Status :: 3 - Alpha
Classifier: Intended Audience :: Developers
Classifier: License :: OSI Approved :: GNU General Public License v3 (GPLv3)
Classifier: Programming Language :: Python :: 3
Classifier: Programming Language :: Python :: 3.10
Classifier: Programming Language :: Python :: 3.11
Classifier: Programming Language :: Python :: 3.12
Requires-Dist: markdown (==3.4.3)
Requires-Dist: markdown-pdf (==1.0)
Requires-Dist: texteditor (==1.4.1)
Project-URL: Documentation, https://github.com/jontok/Notpy/blob/master/README.md
Project-URL: Repository, https://github.com/jontok/Notpy
